README.md
setup.py
researchgate_driver/__init__.py
researchgate_driver.egg-info/PKG-INFO
researchgate_driver.egg-info/SOURCES.txt
researchgate_driver.egg-info/dependency_links.txt
researchgate_driver.egg-info/not-zip-safe
researchgate_driver.egg-info/requires.txt
researchgate_driver.egg-info/top_level.txt