Metadata-Version: 2.1
Name: researchgate-driver
Version: 0.0.2
Summary: Research Gate Social Net controller.
Home-page: https://github.com/drivernet/researchgate_driver
Author: Mindey
Author-email: mindey@qq.com
License: ASK FOR PERMISSIONS
Platform: UNKNOWN
Provides-Extra: test
